imem.v
module imem (
    input [31:0] addr,
    output [31:0] instr
);
reg [31:0] memory [0:255]; // 256 words of memory

initial begin
    $readmemh("program.mem", memory); 
end

assign instr = memory[addr[9:2]]; // Assuming word-aligned addresses (4 bytes per instruction)

endmodule

src/mux2.v
module mux2 (
    input [31:0] a,
    input [31:0] b,
    input sel,
    output [31:0] y
);

assign y = sel ? b : a; // If sel is 1, output b; otherwise, output a
endmodule

pc.v
module pc (
    input clk,
    input reset,
    input [31:0] next_pc,
    output reg [31:0] pc
);

always @(posedge clk or posedge reset) begin
    if (reset)
        pc <= 32'b0; // Reset PC to 0
    else
        pc <= next_pc;
end
    
endmodule

src/if_stage.v
module if_stage (
    input clk,
    input reset,

    input PCsel,
    input [31:0] branch_target,

    output [31:0] instr
);
 wire [31:0] pc;
 wire [31:0] pc_plus4;
 wire [31:0] next_pc;

 pc pc_inst (
     .clk(clk),
     .reset(reset),
     .next_pc(next_pc),
     .pc(pc)
 );

 assign pc_plus4 = pc + 4; 

 mux2 pc_mux (
     .a(pc_plus4),
     .b(branch_target),
     .sel(PCsel),
     .y(next_pc)
 );
 
 imem imem_inst (
     .addr(pc),
     .instr(instr)
 );
 //noi pc tu pc.v vao address cua imem.v , instr tu if_stage.v vao output cua imem.v
 
 always @(posedge clk) begin
    if (reset)
        $display("RESET active -> PC = %h", pc);
    else
        $display("Time=%0t | PC=%h | PC+4=%h | next_PC=%h | PCsel=%b | instr=%h",
          $time, pc, pc_plus4, next_pc, PCsel, instr);
end
 endmodule

testbench/testbench_if_stage.v
module testbench_if_stage;

reg clk;
reg reset;

reg PCsel;
reg [31:0] branch_target;

wire [31:0] instr;  

if_stage uut (
    .clk(clk),
    .reset(reset),
    .PCsel(PCsel),
    .branch_target(branch_target),
    .instr(instr)
);

initial begin
    $dumpfile("wave.vcd");
    $dumpvars(0, testbench_if_stage);
end

initial begin
    clk = 0;
    forever #5 clk = ~clk; // Clock with a period of 10 time units
end

initial begin
    reset = 1;
    PCsel = 0; // Start with PCsel = 0 (sequential execution)
    branch_target = 32'h00000010; 
    #10; 
    reset = 0; 

    #260; // Wait for a few clock cycles to observe sequential execution

    // Test branch taken
    PCsel = 1; // Set PCsel to 1 to take the branch
    #20; 

    PCsel = 0; // Set PCsel back to 0 for sequential execution
    #60; 
    
    $finish; 
end

endmodule

wave.vcd
$date
	Thu Apr  9 22:17:36 2026
$end
$version
	Icarus Verilog
$end
$timescale
	1s
$end
$scope module testbench_if_stage $end
$var wire 32 ! instr [31:0] $end
$var reg 1 " PCsel $end
$var reg 32 # branch_target [31:0] $end
$var reg 1 $ clk $end
$var reg 1 % reset $end
$scope module uut $end
$var wire 1 " PCsel $end
$var wire 32 & branch_target [31:0] $end
$var wire 1 $ clk $end
$var wire 1 % reset $end
$var wire 32 ' pc_plus4 [31:0] $end
$var wire 32 ( pc [31:0] $end
$var wire 32 ) next_pc [31:0] $end
$var wire 32 * instr [31:0] $end
$scope module imem_inst $end
$var wire 32 + instr [31:0] $end
$var wire 32 , addr [31:0] $end
$upscope $end
$scope module pc_inst $end
$var wire 1 $ clk $end
$var wire 1 % reset $end
$var wire 32 - next_pc [31:0] $end
$var reg 32 . pc [31:0] $end
$upscope $end
$scope module pc_mux $end
$var wire 32 / a [31:0] $end
$var wire 32 0 b [31:0] $end
$var wire 1 " sel $end
$var wire 32 1 y [31:0] $end
$upscope $end
$upscope $end
$upscope $end
$enddefinitions $end
$comment Show the parameter values. $end
$dumpall
$end
#0
$dumpvars
b100 1
b10000 0
b100 /
b0 .
b100 -
b0 ,
b10000010100110111 +
b10000010100110111 *
b100 )
b0 (
b100 '
b10000 &
1%
0$
b10000 #
0"
b10000010100110111 !
$end
#5
1$
#10
0$
0%
#15
b10100000000000010010011 !
b10100000000000010010011 *
b10100000000000010010011 +
b1000 )
b1000 -
b1000 1
b1000 '
b1000 /
b100 (
b100 ,
b100 .
1$
#20
0$
#25
b100000000000100010011 !
b100000000000100010011 *
b100000000000100010011 +
b1100 )
b1100 -
b1100 1
b1100 '
b1100 /
b1000 (
b1000 ,
b1000 .
1$
#30
0$
#35
b10000000001000000001100011 !
b10000000001000000001100011 *
b10000000001000000001100011 +
b10000 )
b10000 -
b10000 1
b10000 '
b10000 /
b1100 (
b1100 ,
b1100 .
1$
#40
0$
#45
b110010011 !
b110010011 *
b110010011 +
b10100 )
b10100 -
b10100 1
b10100 '
b10100 /
b10000 (
b10000 ,
b10000 .
1$
#50
0$
#55
b1000001000010011 !
b1000001000010011 *
b1000001000010011 +
b11000 )
b11000 -
b11000 1
b11000 '
b11000 /
b10100 (
b10100 ,
b10100 .
1$
#60
0$
#65
b100000000001100011 !
b100000000001100011 *
b100000000001100011 +
b11100 )
b11100 -
b11100 1
b11100 '
b11100 /
b11000 (
b11000 ,
b11000 .
1$
#70
0$
#75
b1000011000000110110011 !
b1000011000000110110011 *
b1000011000000110110011 +
b100000 )
b100000 -
b100000 1
b100000 '
b100000 /
b11100 (
b11100 ,
b11100 .
1$
#80
0$
#85
b11111111111100100000001000010011 !
b11111111111100100000001000010011 *
b11111111111100100000001000010011 +
b100100 )
b100100 -
b100100 1
b100100 '
b100100 /
b100000 (
b100000 ,
b100000 .
1$
#90
0$
#95
b11111111010111111111000001101111 !
b11111111010111111111000001101111 *
b11111111010111111111000001101111 +
b101000 )
b101000 -
b101000 1
b101000 '
b101000 /
b100100 (
b100100 ,
b100100 .
1$
#100
0$
#105
b11000000100010011 !
b11000000100010011 *
b11000000100010011 +
b101100 )
b101100 -
b101100 1
b101100 '
b101100 /
b101000 (
b101000 ,
b101000 .
1$
#110
0$
#115
b11111111111100001000000010010011 !
b11111111111100001000000010010011 *
b11111111111100001000000010010011 +
b110000 )
b110000 -
b110000 1
b110000 '
b110000 /
b101100 (
b101100 ,
b101100 .
1$
#120
0$
#125
b11111101100111111111000001101111 !
b11111101100111111111000001101111 *
b11111101100111111111000001101111 +
b110100 )
b110100 -
b110100 1
b110100 '
b110100 /
b110000 (
b110000 ,
b110000 .
1$
#130
0$
#135
b1001010010000000100011 !
b1001010010000000100011 *
b1001010010000000100011 +
b111000 )
b111000 -
b111000 1
b111000 '
b111000 /
b110100 (
b110100 ,
b110100 .
1$
#140
0$
#145
b10100000000001000010011 !
b10100000000001000010011 *
b10100000000001000010011 +
b111100 )
b111100 -
b111100 1
b111100 '
b111100 /
b111000 (
b111000 ,
b111000 .
1$
#150
0$
#155
b1010010011 !
b1010010011 *
b1010010011 +
b1000000 )
b1000000 -
b1000000 1
b1000000 '
b1000000 /
b111100 (
b111100 ,
b111100 .
1$
#160
0$
#165
b100000000001100010011 !
b100000000001100010011 *
b100000000001100010011 +
b1000100 )
b1000100 -
b1000100 1
b1000100 '
b1000100 /
b1000000 (
b1000000 ,
b1000000 .
1$
#170
0$
#175
b10000000100000000001100011 !
b10000000100000000001100011 *
b10000000100000000001100011 +
b1001000 )
b1001000 -
b1001000 1
b1001000 '
b1001000 /
b1000100 (
b1000100 ,
b1000100 .
1$
#180
0$
#185
b11000101000001110110011 !
b11000101000001110110011 *
b11000101000001110110011 +
b1001100 )
b1001100 -
b1001100 1
b1001100 '
b1001100 /
b1001000 (
b1001000 ,
b1001000 .
1$
#190
0$
#195
b110000001010010011 !
b110000001010010011 *
b110000001010010011 +
b1010000 )
b1010000 -
b1010000 1
b1010000 '
b1010000 /
b1001100 (
b1001100 ,
b1001100 .
1$
#200
0$
#205
b111000001100010011 !
b111000001100010011 *
b111000001100010011 +
b1010100 )
b1010100 -
b1010100 1
b1010100 '
b1010100 /
b1010000 (
b1010000 ,
b1010000 .
1$
#210
0$
#215
b11111111111100100000001000010011 !
b11111111111100100000001000010011 *
b11111111111100100000001000010011 +
b1011000 )
b1011000 -
b1011000 1
b1011000 '
b1011000 /
b1010100 (
b1010100 ,
b1010100 .
1$
#220
0$
#225
b11111110110111111111000001101111 !
b11111110110111111111000001101111 *
b11111110110111111111000001101111 +
b1011100 )
b1011100 -
b1011100 1
b1011100 '
b1011100 /
b1011000 (
b1011000 ,
b1011000 .
1$
#230
0$
#235
b11001010010001000100011 !
b11001010010001000100011 *
b11001010010001000100011 +
b1100000 )
b1100000 -
b1100000 1
b1100000 '
b1100000 /
b1011100 (
b1011100 ,
b1011100 .
1$
#240
0$
#245
b1101111 !
b1101111 *
b1101111 +
b1100100 )
b1100100 -
b1100100 1
b1100100 '
b1100100 /
b1100000 (
b1100000 ,
b1100000 .
1$
#250
0$
#255
bx !
bx *
bx +
b1101000 )
b1101000 -
b1101000 1
b1101000 '
b1101000 /
b1100100 (
b1100100 ,
b1100100 .
1$
#260
0$
#265
b1101100 )
b1101100 -
b1101100 1
b1101100 '
b1101100 /
b1101000 (
b1101000 ,
b1101000 .
1$
#270
b10000 )
b10000 -
b10000 1
0$
1"
#275
b110010011 !
b110010011 *
b110010011 +
b10100 '
b10100 /
b10000 (
b10000 ,
b10000 .
1$
#280
0$
#285
1$
#290
b10100 )
b10100 -
b10100 1
0$
0"
#295
b1000001000010011 !
b1000001000010011 *
b1000001000010011 +
b11000 )
b11000 -
b11000 1
b11000 '
b11000 /
b10100 (
b10100 ,
b10100 .
1$
#300
0$
#305
b100000000001100011 !
b100000000001100011 *
b100000000001100011 +
b11100 )
b11100 -
b11100 1
b11100 '
b11100 /
b11000 (
b11000 ,
b11000 .
1$
#310
0$
#315
b1000011000000110110011 !
b1000011000000110110011 *
b1000011000000110110011 +
b100000 )
b100000 -
b100000 1
b100000 '
b100000 /
b11100 (
b11100 ,
b11100 .
1$
#320
0$
#325
b11111111111100100000001000010011 !
b11111111111100100000001000010011 *
b11111111111100100000001000010011 +
b100100 )
b100100 -
b100100 1
b100100 '
b100100 /
b100000 (
b100000 ,
b100000 .
1$
#330
0$
#335
b11111111010111111111000001101111 !
b11111111010111111111000001101111 *
b11111111010111111111000001101111 +
b101000 )
b101000 -
b101000 1
b101000 '
b101000 /
b100100 (
b100100 ,
b100100 .
1$
#340
0$
#345
b11000000100010011 !
b11000000100010011 *
b11000000100010011 +
b101100 )
b101100 -
b101100 1
b101100 '
b101100 /
b101000 (
b101000 ,
b101000 .
1$
