imem.v
module imem (
    input [31:0] addr,
    output [31:0] instr
);
reg [31:0] memory [0:255]; // 256 words of memory

initial begin
    $readmemh("program.mem", memory); 
end

assign instr = memory[addr[9:2]]; // Assuming word-aligned addresses (4 bytes per instruction)

endmodule

pc.v
module pc (
    input clk,
    input reset,
    input [31:0] next_pc,
    output reg [31:0] pc
);

always @(posedge clk or posedge reset) begin
    if (reset)
        pc <= 32'b0; // Reset PC to 0
    else
        pc <= next_pc;
end
    
endmodule

if_stage.v
module if_stage (
    input clk,
    input reset,
    output [31:0] instr
);
 wire [31:0] pc;
 wire [31:0] next_pc;

 pc pc_inst (
     .clk(clk),
     .reset(reset),
     .next_pc(next_pc),
     .pc(pc)
 );

 assign next_pc = pc + 4; // Simple increment for the next PC, can be modified as needed
 imem imem_inst (
     .addr(pc),
     .instr(instr)
 );
 //noi pc tu pc.v vao address cua imem.v , instr tu if_stage.v vao output cua imem.v
 
 always @(posedge clk) begin
    if (reset)
        $display("RESET active -> PC = %h", pc);
    else
        $display("Time=%0t | PC=%h | next_PC=%h | instruction=%h", 
                  $time, pc, next_pc, instr);
end
 endmodule

testbench_if_stage.v
module testbench_if_stage;

reg clk;
reg reset;
wire [31:0] instr;  

if_stage uut (
    .clk(clk),
    .reset(reset),
    .instr(instr)
);

initial begin
    $dumpfile("wave.vcd");
    $dumpvars(0, testbench_if_stage);
end

initial begin
    clk = 0;
    forever #5 clk = ~clk; // Clock with a period of 10 time units
end

initial begin
    reset = 1;
    #10; // Hold reset for 10 time units
    reset = 0; // Release reset
     #100 $finish; // Run the simulation for 100 time units after releasing reset
end

endmodule

wave.vcd
$date
	Fri Apr  3 08:12:04 2026
$end
$version
	Icarus Verilog
$end
$timescale
	1s
$end
$scope module testbench_if_stage $end
$var wire 32 ! instr [31:0] $end
$var reg 1 " clk $end
$var reg 1 # reset $end
$scope module uut $end
$var wire 1 " clk $end
$var wire 1 # reset $end
$var wire 32 $ pc [31:0] $end
$var wire 32 % next_pc [31:0] $end
$var wire 32 & instr [31:0] $end
$scope module imem_inst $end
$var wire 32 ' instr [31:0] $end
$var wire 32 ( addr [31:0] $end
$upscope $end
$scope module pc_inst $end
$var wire 1 " clk $end
$var wire 32 ) next_pc [31:0] $end
$var wire 1 # reset $end
$var reg 32 * pc [31:0] $end
$upscope $end
$upscope $end
$upscope $end
$enddefinitions $end
$comment Show the parameter values. $end
$dumpall
$end
#0
$dumpvars
b0 *
b100 )
b0 (
b10011 '
b10011 &
b100 %
b0 $
1#
0"
b10011 !
$end
#5
1"
#10
0"
0#
#15
b10000000000000010010011 !
b10000000000000010010011 &
b10000000000000010010011 '
b1000 %
b1000 )
b100 $
b100 (
b100 *
1"
#20
0"
#25
b100000000000100010011 !
b100000000000100010011 &
b100000000000100010011 '
b1100 %
b1100 )
b1000 $
b1000 (
b1000 *
1"
#30
0"
#35
b1000001000000110110011 !
b1000001000000110110011 &
b1000001000000110110011 '
b10000 %
b10000 )
b1100 $
b1100 (
b1100 *
1"
#40
0"
#45
b1100010000001000110011 !
b1100010000001000110011 &
b1100010000001000110011 '
b10100 %
b10100 )
b10000 $
b10000 (
b10000 *
1"
#50
0"
#55
bx !
bx &
bx '
b11000 %
b11000 )
b10100 $
b10100 (
b10100 *
1"
#60
0"
#65
b11100 %
b11100 )
b11000 $
b11000 (
b11000 *
1"
#70
0"
#75
b100000 %
b100000 )
b11100 $
b11100 (
b11100 *
1"
#80
0"
#85
b100100 %
b100100 )
b100000 $
b100000 (
b100000 *
1"
#90
0"
#95
b101000 %
b101000 )
b100100 $
b100100 (
b100100 *
1"
#100
0"
#105
b101100 %
b101100 )
b101000 $
b101000 (
b101000 *
1"
